<?xml version="1.0" encoding="UTF-16"?>
<resources>	
	
	<!-- ai trees -->
	<res alias="ai\combat\npc_tactic_vampiress"							path="dlc\bob\data\gameplay\trees\monster_bruxa_logic.w2behtree"/>
	<res alias="ai\monsters/monster_sharley_logic"						path="dlc\bob\data\gameplay\trees\monster_sharley_logic.w2behtree"/>
	<res alias="ai\monsters/monster_dettlaff_tornado_logic"				path="dlc\bob\data\gameplay\trees\dettlaff_tornado_logic.w2behtree"/>
	<res alias="ai\monsters/monster_black_spider_ep2_logic"				path="dlc\bob\data\gameplay\trees\monster_black_spider_ep2_logic.w2behtree"/>
	<res alias="ai\monsters/monster_boar_ep2_logic"						path="dlc\bob\data\gameplay\trees\monster_boar_ep2_logic.w2behtree"/>
	<res alias="ai\monsters/monster_gravier_logic"						path="dlc\bob\data\gameplay\trees\monster_gravier_logic.w2behtree"/>
	<res alias="ai\monsters\monster_barghest_logic" 					path="dlc\bob\data\gameplay\trees\monster_barghest_logic.w2behtree"/>
	<res alias="ai\monsters\monster_bigbadwolf_logic"					path="gameplay\trees\monsters\monster_werewolf_logic.w2behtree"/>
	<res alias="ai\monsters\monster_dracolizard_logic" 					path="dlc\bob\data\gameplay\trees\monster_dracolizard_logic.w2behtree"/>
	<res alias="ai\monsters\monster_banshee_logic" 						path="dlc\bob\data\gameplay\trees\monster_banshee_logic.w2behtree"/>
	<res alias="ai\monster_spawn_banshee"								path="dlc\bob\data\gameplay\trees\monster_banshee_spawn.w2behtree" />	
	<res alias="ai\monster_death_banshee"								path="dlc\bob\data\gameplay\trees\monster_banshee_death.w2behtree" />
	<res alias="ai\monsters/monster_broom_logic" 						path="dlc\bob\data\gameplay\trees\monster_broom_logic.w2behtree"/>
	<res alias="ai\idle\echinops_idle_decorator"						path="dlc\bob\data\gameplay\trees\monster_echinops_idle_logic.w2behtree" />
	<res alias="ai\monsters/monster_panther_logic"						path="dlc\bob\data\gameplay\trees\monster_panther_logic.w2behtree"/>
	<res alias="ai\monsters/monster_kikimore_logic"						path="dlc\bob\data\gameplay\trees\monster_kikimore_logic.w2behtree"/>
	<res alias="ai\monsters/monster_scolopendromorph_logic" 			path="dlc\bob\data\gameplay\trees\monster_scolopendromorph_logic.w2behtree" />
	<res alias="ai\monsters/monster_echinops_logic" 					path="dlc\bob\data\gameplay\trees\monster_echinops_logic.w2behtree" />
	<res alias="ai\monsters/monster_dettlaff_vampire_logic" 			path="dlc\bob\data\gameplay\trees\monster_dettlaff_vampire_logic.w2behtree" />
	<res alias="ai\monsters/monster_dettlaff_vampire_counter" 			path="dlc\bob\data\gameplay\trees\monster_dettlaff_vampire_counter.w2behtree" />
	<res alias="ai\monsters/monster_dettlaff_vampire_parry" 			path="dlc\bob\data\gameplay\trees\monster_dettlaff_vampire_parry.w2behtree" />
	<res alias="ai\monsters/monster_dettlaff_vampire_counter_after_hit" path="dlc\bob\data\gameplay\trees\monster_dettlaff_vampire_counter_after_hit.w2behtree" />
	<res alias="ai\monsters/npc_tactic_gregoire" 						path="dlc\bob\data\gameplay\trees\npc_tactic_gregoire.w2behtree" />
	<res alias="ai\combat\npc_def_gregoire_counter" 					path="dlc\bob\data\gameplay\trees\npc_def_gregoire_counter.w2behtree" />
	<res alias="ai\monsters\monster_wight_logic" 						path="dlc\bob\data\gameplay\trees\monster_wight_logic.w2behtree"/>
	<res alias="ai\monsters/monster_dettlaff_logic"						path="dlc\bob\data\gameplay\trees\monster_dettlaff_logic.w2behtree" />
	<res alias="ai\monsters/monster_dettlaff_minion_logic"				path="dlc\bob\data\gameplay\trees\monster_dettlaff_minion_logic.w2behtree" />
	<res alias="ai\monsters/monster_dettlaff_minion_parry" 				path="dlc\bob\data\gameplay\trees\monster_dettlaff_minion_parry.w2behtree" />
	<res alias="ai\monsters/monster_dettlaff_minion_counter" 			path="dlc\bob\data\gameplay\trees\monster_dettlaff_minion_counter.w2behtree" />
	<res alias="ai\monsters\monster_fairytale_witch_logic" 				path="dlc\bob\data\gameplay\trees\monster_fairytale_witch_logic.w2behtree"/>
		
	<!-- npc entities -->
	<res alias="bruxa"												path="dlc\bob\data\characters\npc_entities\monsters\bruxa.w2ent" />
	<res alias="bruxa_cloak"										path="dlc\bob\data\characters\npc_entities\monsters\bruxa_cloak.w2ent" />
	<res alias="bruxa_commoner"										path="dlc\bob\data\characters\npc_entities\monsters\bruxa_cloak.w2ent" />
	<res alias="alpor"												path="dlc\bob\data\characters\npc_entities\monsters\bruxa_alp.w2ent" />
	<res alias="alp"												path="dlc\bob\data\characters\npc_entities\monsters\bruxa_alp.w2ent" />
	<res alias="sharley"											path="dlc\bob\data\characters\npc_entities\monsters\sharley.w2ent" />
	<res alias="panther"											path="dlc\bob\data\characters\npc_entities\monsters\panther_black.w2ent" />
	<res alias="tornado"											path="dlc\bob\data\fx\monsters\dettlaff\dettlaff_swarm_tornado.w2ent" />
	<res alias="black_spider_ep2"									path="dlc\bob\data\characters\npc_entities\monsters\black_spider_ep2.w2ent" />
	<res alias="black_spider_large_ep2"								path="dlc\bob\data\characters\npc_entities\monsters\black_spider_large_ep2.w2ent" />
	<res alias="boar_ep2"											path="dlc\bob\data\characters\npc_entities\monsters\wild_boar_ep2.w2ent" />
	<res alias="fleder"												path="dlc\bob\data\characters\npc_entities\monsters\fleder.w2ent" />
	<res alias="garkain"											path="dlc\bob\data\characters\npc_entities\monsters\garkain.w2ent" />
	<res alias="gravier"											path="dlc\bob\data\characters\npc_entities\monsters\gravier.w2ent" />
	<res alias="knight_giant"										path="dlc\bob\data\characters\npc_entities\monsters\q701_dagonet_giant.w2ent" />
	<res alias="q701_giant"											path="dlc\bob\data\characters\npc_entities\monsters\q701_dagonet_giant.w2ent" />
	<res alias="dagonet"											path="dlc\bob\data\characters\npc_entities\monsters\q701_dagonet_giant.w2ent" />
	<res alias="dagonet_giant"										path="dlc\bob\data\characters\npc_entities\monsters\q701_dagonet_giant.w2ent" />
	<res alias="q701_dagonet_giant"									path="dlc\bob\data\characters\npc_entities\monsters\q701_dagonet_giant.w2ent" />
	<res alias="q704_cloud_giant"									path="dlc\bob\data\characters\npc_entities\monsters\q704_cloud_giant.w2ent" />
	<res alias="cloud_giant"										path="dlc\bob\data\characters\npc_entities\monsters\q704_cloud_giant.w2ent" />
	<res alias="sprigan"											path="dlc\bob\data\characters\npc_entities\monsters\spriggan.w2ent" />
	<res alias="lynx"												path="dlc\bob\data\characters\npc_entities\secondary_npc\lynx_rock_witch.w2ent" />
	<res alias="sheep_ep2"											path="dlc\bob\data\characters\npc_entities\animals\sheep_ep2.w2ent" />
	<res alias="banshee"											path="dlc\bob\data\characters\npc_entities\monsters\nightwraith_banshee.w2ent" />
	<res alias="skeleton"											path="dlc\bob\data\characters\npc_entities\monsters\nightwraith_banshee_summon.w2ent" />
	<res alias="skeleton_generic"									path="dlc\bob\data\characters\npc_entities\monsters\nightwraith_banshee_summon_skeleton.w2ent" />
	<res alias="bigbadwolf"											path="dlc\bob\data\characters\npc_entities\monsters\bigbadwolf.w2ent"/>
	<res alias="dracolizard"										path="dlc\bob\data\characters\npc_entities\monsters\oszluzg.w2ent"/>
	<res alias="drake"												path="dlc\bob\data\characters\npc_entities\monsters\oszluzg.w2ent"/>
	<res alias="oszluzg"											path="dlc\bob\data\characters\npc_entities\monsters\oszluzg.w2ent"/>
	<res alias="barghest"											path="dlc\bob\data\characters\npc_entities\monsters\barghest.w2ent"/>
	<res alias="regis_vampire"										path="dlc\bob\data\characters\npc_entities\monsters\regis_vampire.w2ent"/>
	<res alias="q704_ft_pixie_01"									path="dlc\bob\data\quests\main_quests\quest_files\q704b_fairy_tale\entities\imps\q704_ft_pixie_01.w2ent"/>
	<res alias="mq7006_hermit"										path="dlc\bob\data\quests\minor_quests\quest_files\mq7006_the_paths_of_destiny\characters\mq7006_hermit.w2ent"/>
	<res alias="panther_fairytale_witch"							path="dlc\bob\data\characters\npc_entities\monsters\panther_black_fairytale_witch.w2ent"/>
	<res alias="broom"												path="dlc\bob\data\items\quest_items\q704\q704_item__evil_witch_broom.w2ent"/>
	<res alias="q703_enchanter_carpet"								path="dlc\bob\data\quests\main_quests\quest_files\q703_all_for_one\characters\mandragora_nobles\ofir_enchanter_files\q703_enchanter_carpet.w2ent"/>
	<res alias="dolphin"											path="dlc\bob\data\characters\npc_entities\animals\dolphin.w2ent"/>
	<res alias="peacock"											path="dlc\bob\data\characters\npc_entities\animals\peacock.w2ent" chunk="content4" />
	<res alias="pheasant"											path="dlc\bob\data\characters\npc_entities\animals\pheasant.w2ent" chunk="content4" />
	<res alias="dettlaff"											path="dlc\bob\data\characters\npc_entities\monsters\detlaff_monster.w2ent" />
	<res alias="construct"											path="dlc\bob\data\quests\main_quests\quest_files\q704_truth\characters\detlaff_construct.w2ent"/>
	<res alias="noblef"												path="dlc\bob\data\characters\npc_entities\crowd_npc\bob_citizen\bob_noble_female.w2ent" />
	<res alias="scolopendromorph"									path="dlc\bob\data\characters\npc_entities\monsters\scolopendromorph.w2ent" chunk="content4" />
	<res alias="archespor_normal"									path="dlc\bob\data\characters\npc_entities\monsters\echinops_normal.w2ent" chunk="content4" />
	<res alias="archespor_normal_lw"								path="dlc\bob\data\characters\npc_entities\monsters\echinops_normal_lw.w2ent" chunk="content4" />
	<res alias="archespor_hard"										path="dlc\bob\data\characters\npc_entities\monsters\echinops_hard.w2ent" chunk="content4" />
	<res alias="archespor_turret"									path="dlc\bob\data\characters\npc_entities\monsters\echinops_turret.w2ent" chunk="content4" />
	<res alias="archespor_base_normal"								path="dlc\bob\data\characters\npc_entities\monsters\echinops_base_normal.w2ent" chunk="content4" />
	<res alias="archespor_base_normal_lw"							path="dlc\bob\data\characters\npc_entities\monsters\echinops_base_normal_lw.w2ent" chunk="content4" />
	<res alias="archespor_base_hard"								path="dlc\bob\data\characters\npc_entities\monsters\echinops_base_hard.w2ent" chunk="content4" />
	<res alias="archespor_base_turret"								path="dlc\bob\data\characters\npc_entities\monsters\echinops_base_turret.w2ent" chunk="content4" />
	<res alias="dettlaff_vampire"									path="dlc\bob\data\characters\npc_entities\monsters\dettlaff_vampire.w2ent" chunk="content4" />
	<res alias="kikimore"											path="dlc\bob\data\characters\npc_entities\monsters\kikimore.w2ent" />
	<res alias="kikimore_small"										path="dlc\bob\data\characters\npc_entities\monsters\kikimore_small.w2ent" />
	<res alias="barghest_wight_minion" 								path="dlc\bob\data\characters\npc_entities\monsters\barghest_wight_minion.w2ent"/>
	<res alias="wight" 												path="dlc\bob\data\characters\npc_entities\monsters\wicht.w2ent"/>
	<res alias="spooncollector" 									path="dlc\bob\data\characters\npc_entities\monsters\spooncollector.w2ent"/>
	<res alias="fairytale_witch" 									path="dlc\bob\data\characters\npc_entities\monsters\fairytale_witch.w2ent"/>
	<res alias="gregoire"											path="dlc\bob\data\quests\sidequests\quest_files\sq701_tournament\characters\sq701_gregoire.w2ent" chunk="content4" />
	<res alias="champion"											path="dlc\bob\data\quests\sidequests\quest_files\sq701_tournament\characters\sq701_gregoire.w2ent" chunk="content4" />
	<res alias="gargoyle_bob" 										path="dlc\bob\data\characters\npc_entities\monsters\gargoyle_lvl1.w2ent"/>
	<res alias="hanza_shield" 										path="dlc\bob\data\living_world\enemy_templates\raider_half_elf.w2ent"/>
	<res alias="q704_city_bruxa" 									path="dlc\bob\data\quests\main_quests\quest_files\q704_truth\characters\q704_bruxa_city.w2ent"/>	
	<res alias="bruxa_alp_mid" 										path="dlc\bob\data\living_world\enemy_templates\bruxa_alp_mid.w2ent"/>	
	<res alias="bruxa_mid" 											path="dlc\bob\data\living_world\enemy_templates\bruxa_mid.w2ent"/>	
	<res alias="raider_axe_late" 									path="dlc\bob\data\living_world\enemy_templates\raider_lvl1_axe_late.w2ent"/>	
	<res alias="raider_axe_mid" 									path="dlc\bob\data\living_world\enemy_templates\raider_lvl1_axe_mid.w2ent"/>	
	<res alias="raider_mace_early" 									path="dlc\bob\data\living_world\enemy_templates\raider_lvl1_mace_early.w2ent"/>	
	<res alias="raider_mace_late" 									path="dlc\bob\data\living_world\enemy_templates\raider_lvl1_mace_late.w2ent"/>	
	<res alias="raider_mace_mid" 									path="dlc\bob\data\living_world\enemy_templates\raider_lvl1_mace_mid.w2ent"/>	
	<res alias="raider_sword_early" 								path="dlc\bob\data\living_world\enemy_templates\raider_lvl1_sword_early.w2ent"/>	
	<res alias="raider_sword_late" 									path="dlc\bob\data\living_world\enemy_templates\raider_lvl1_sword_late.w2ent"/>	
	<res alias="raider_sword_mid" 									path="dlc\bob\data\living_world\enemy_templates\raider_lvl1_sword_mid.w2ent"/>	
	<res alias="raider_torch_early" 								path="dlc\bob\data\living_world\enemy_templates\raider_lvl1_torch_early.w2ent"/>
	<res alias="q704_ft_unicorn_syanna" 							path="dlc\bob\data\quests\main_quests\quest_files\q704b_fairy_tale\entities\syanna_unicorn\q704_ft_syanna_unicorn.w2ent"/>
	
	
	
	<!-- fx entities -->
	<res alias="target_dummy_entity"								path="dlc\bob\data\gameplay\abilities\sharley\target_dummy_entity.w2ent" />
	<res alias="detection_player_fx"								path="dlc\bob\data\fx\monsters\sharley\detection\detection_player_fx.w2ent" />
	<res alias="sharley_igni_armor_hit"								path="dlc\bob\data\fx\monsters\sharley\igni\igni_armor_hit.w2ent" />
	<res alias="bruxa_scream_attack"								path="dlc\bob\data\gameplay\abilities\bruxa\bruxa_scream_attack.w2ent" />
	<res alias="mutation_2_explode"									path="dlc\bob\data\fx\gameplay\mutation\mutation_2\mutation_2_explode.w2ent" />
	<res alias="barghest_force"										path="dlc\bob\data\fx\monsters\barghest\barghest_ghost_force.w2ent" />
	<res alias="sprigan_special_attack"								path="dlc\bob\data\fx\monsters\spriggan\attack_02\sprigan_special_attack.w2ent" />
	<res alias="ep2_sorceress_stone_proj"							path="dlc\bob\data\gameplay\abilities\lynx_rock_witch\lynx_rock_witch_rock.w2ent" />
	<res alias="ep2_magic_attack_lightning"							path="dlc\bob\data\gameplay\abilities\lynx_rock_witch\lynx_rock_witch_slashes.w2ent" />
	<res alias="lynx_cast"											path="dlc\bob\data\gameplay\abilities\lynx_rock_witch\lynx_rock_witch_cast.w2ent" />
	<res alias="dracolizard_fire_projectile"						path="dlc\bob\data\gameplay\abilities\dracolizard\dracolizard_fire_projectile.w2ent" />
	<res alias="ground_fx"											path="dlc\bob\data\fx\monsters\knight_giant\ground_fx.w2ent" />
	<res alias="mutation2_critical"									path="dlc\bob\data\fx\gameplay\mutation\mutation_2\mutation_2_critical_force.w2ent" />
	<res alias="ground_trail_fx"									path="dlc\bob\data\fx\monsters\knight_giant\ground_trail_fx.w2ent" />
	<res alias="giant_shockwave_proj"								path="dlc\bob\data\gameplay\abilities\giant\giant_shockwave_proj.w2ent" />
	<res alias="dracolizard_ground_fire"							path="dlc\bob\data\gameplay\abilities\dracolizard\dracolizard_ground_fire.w2ent" />
	<res alias="mutation9_hit"										path="dlc\bob\data\fx\gameplay\mutation\mutation_9\mutation_9_hit.w2ent" />
	<res alias="mutation1_hit"										path="dlc\bob\data\fx\gameplay\mutation\mutation_1\mutation_1_hit.w2ent" />
	<res alias="witch_fluid"										path="dlc\bob\data\fx\monsters\fairytale_witch\liquid_hit_ground.w2ent" />
	<res alias="corpse_torso"										path="dlc\bob\data\characters\models\common\wounds\severed_man_top.w2ent" />
	<res alias="corpse_legs"										path="dlc\bob\data\characters\models\common\wounds\severed_man_botom.w2ent" />
	<res alias="fairytale_witch_shield_hit"							path="dlc\bob\data\fx\monsters\fairytale_witch\shield\fairytale_shield_hit.w2ent" />
	<res alias="hit_wall_arena_decal_fx"							path="dlc\bob\data\fx\monsters\sharley\dust\hit_wall_arena_decal_fx.w2ent" />
	<res alias="magic_attack_water"									path="dlc\bob\data\gameplay\abilities\water_mage\sand_gusts_bob.w2ent"/>
	<res alias="tornado_water_entity"								path="dlc\bob\data\gameplay\abilities\water_mage\tornado_bob.w2ent" chunk="content4"/>
	<res alias="water_coil_proj"									path="dlc\bob\data\gameplay\abilities\water_mage\sand_coil_proj_bob.w2ent" />
	<res alias="waterTrap"											path="dlc\bob\data\gameplay\abilities\water_mage\sand_trap_bob.w2ent" chunk="content4" />
	<res alias="water_push_cast"									path="dlc\bob\data\gameplay\abilities\water_mage\sand_push_cast_bob.w2ent" chunk="content4" />
	<res alias="water_quicksand"									path="dlc\bob\data\gameplay\abilities\water_mage\quick_sand_bob.w2ent" chunk="content4" />
	<res alias="cloud_giant_weapon_hit"								path="dlc\bob\data\fx\monsters\cloud_giant\cloud_giant_weapon_hit.w2ent" chunk="content4" />
	<res alias="alp_teleport_trail"									path="dlc\bob\data\fx\monsters\bruxa\alp_teleport_trail.w2ent" chunk="content4" />
	<res alias="spooncollector_despawn"								path="dlc\bob\data\fx\monsters\spooncollector\spooncollector_despawn.w2ent" chunk="content4" />
	<res alias="mutation7_sonar"									path="dlc\bob\data\fx\gameplay\mutation\mutation_7\mutation_7.w2ent" />
	<res alias="mutation7_flash"									path="dlc\bob\data\fx\gameplay\mutation\mutation_7\mutation_7_flash.w2ent" />
	<res alias="scolo_fx_entity"									path="dlc\bob\data\fx\monsters\scolopendromorph\scolopendromorph_base_effect.w2ent"/>
	<res alias="kiki_splat"											path="dlc\bob\data\fx\monsters\kikimore\ground_fx.w2ent"/>
	<res alias="underground_fx"										path="dlc\bob\data\fx\monsters\kikimore\underground_fx.w2ent"/>
	<res alias="fairytale_witch_disappear"							path="dlc\bob\data\fx\monsters\fairytale_witch\teleport\fairytale_disappear.w2ent"/>
	<res alias="fairytale_witch_appear"								path="dlc\bob\data\fx\monsters\fairytale_witch\teleport\fairytale_appear.w2ent"/>
	
	<!-- projectiles -->
	<res alias="sharley_shockwave_proj"								path="dlc\bob\data\gameplay\abilities\sharley\sharley_shockwave_proj.w2ent" />
	<res alias="sharley_stone_proj"									path="dlc\bob\data\gameplay\abilities\sharley\sharley_stone_proj.w2ent" />
	<res alias="dettlaff_swarm_projectile"							path="dlc\bob\data\gameplay\abilities\dettlaff_monster\dettlaff_swarm_projectile.w2ent" />
	<res alias="root_lance_proj"									path="dlc\bob\data\gameplay\abilities\sprigan\root_lance_proj.w2ent" />
	<res alias="bruxa_spawn_proj"									path="dlc\bob\data\gameplay\abilities\bruxa\bruxa_spawn_proj.w2ent" />
	<res alias="blood_proj"											path="dlc\bob\data\gameplay\abilities\dettlaff_monster\blood_projectile.w2ent" />
	<res alias="witch_spawn_proj"									path="dlc\bob\data\fx\monsters\fairytale_witch\fairytale_witch_spawn_projectile.w2ent" />
	<res alias="spooncollector_ground_proj"							path="dlc\bob\data\fx\monsters\spooncollector\spooncollector_move.w2ent" />
	<res alias="archespor_acid"										path="dlc\bob\data\fx\monsters\echinops\echinops_acid_projectile.w2ent"/>
	<res alias="archespor_sfx_projectile"							path="dlc\bob\data\fx\monsters\echinops\echinops_sfx_projectile.w2ent"/>
	<res alias="fairytale_witch_projectile"							path="dlc\bob\data\fx\monsters\fairytale_witch\fairytale_witch_projectile.w2ent"/>
	<res alias="spooncollector_spit_projectile"						path="dlc\bob\data\gameplay\abilities\wight\wight_spit_proj.w2ent"/>
	<res alias="scolopendromorph_venom"								path="dlc\bob\data\fx\monsters\scolopendromorph\scolopendromorph_venom_projectile.w2ent"/>
	
	<!-- other -->
	<res alias="giant_lightning_strike"								path="dlc\bob\data\gameplay\abilities\giant\giant_lightning_strike.w2ent" />
	<res alias="sprigan_root_attack"								path="dlc\bob\data\gameplay\abilities\sprigan\sprigan_root_attack.w2ent" />
	<res alias="dettlaff_trap"										path="dlc\bob\data\fx\monsters\dettlaff\monster\dettlaff_monster_trap.w2ent" />
	<res alias="explosion_dismember_force"							path="characters\models\common\special\force.w2ent" />
	
	<!-- journal bestiary -->
	<res alias="BestiaryPanther"									path="dlc\bob\journal\bestiary\panther.journal"/>
	<res alias="BestiaryDracolizard"								path="dlc\bob\journal\bestiary\dracolizard.journal"/>
	<res alias="BestiaryDracolizardMatriarch"						path="dlc\bob\journal\bestiary\mq7010dracolizard.journal"/>
	<res alias="BestiarySharley"									path="dlc\bob\journal\bestiary\ep2sharley.journal"/>
	<res alias="BestiaryBarghest"									path="dlc\bob\journal\bestiary\barghests.journal"/>
	<res alias="BestiaryGarkain"									path="dlc\bob\journal\bestiary\garkain.journal"/>
	<res alias="BestiaryBruxa"										path="dlc\bob\journal\bestiary\bruxa.journal"/>
	<res alias="BestiaryFleder"										path="dlc\bob\journal\bestiary\fleder.journal"/>
	<res alias="BestiaryAlp"										path="dlc\bob\journal\bestiary\alp.journal"/>
	<res alias="BestiaryScolopendromorph"							path="dlc\bob\journal\bestiary\scolopedromorph.journal"/>
	<res alias="BestiaryPaleWidow"									path="dlc\bob\journal\bestiary\palewidow.journal"/>
	<res alias="BestiaryKikimoraWarrior"							path="dlc\bob\journal\bestiary\kikimora.journal"/>
	<res alias="BestiaryKikimoraWorker"								path="dlc\bob\journal\bestiary\kikimoraworker.journal"/>
	<res alias="BestiaryArchespore"									path="dlc\bob\journal\bestiary\archespore.journal"/>
	<res alias="BestiaryDarkPixie"									path="dlc\bob\journal\bestiary\darkpixies.journal"/>
	<res alias="BestiaryGraveir"									path="dlc\bob\journal\bestiary\parszywiec.journal"/>
	<res alias="BestiaryWicht"										path="dlc\bob\journal\bestiary\wicht.journal"/>
	<res alias="BestiaryDagonet"									path="dlc\bob\journal\bestiary\dagonet.journal"/>
	<res alias="BestiaryCloudGiant"									path="dlc\bob\journal\bestiary\q704cloudgiant.journal"/>
	<res alias="BestiarySpriggan"									path="dlc\bob\journal\bestiary\mq7002spriggan.journal"/>
	<res alias="BestiaryProtofleder"								path="dlc\bob\journal\bestiary\protofleder.journal"/>
	<res alias="BestiaryBigBadWolf"									path="dlc\bob\journal\bestiary\q704bigbadwolfasbeast.journal"/>
	<res alias="BestiaryPigsEvil"									path="dlc\bob\journal\bestiary\q704threelittlepigs.journal"/>
	<res alias="BestiaryLastBasilisk"								path="dlc\bob\journal\bestiary\mq7018basilisk.journal"/>
	<res alias="BestiaryFairtaleWitch"								path="dlc\bob\journal\bestiary\q704ftwitch.journal"/>
	<res alias="BestiaryRapunzel"									path="dlc\bob\journal\bestiary\q704rapunzel.journal"/>
	<res alias="BestiaryBeanshie"									path="dlc\bob\journal\bestiary\beanshie.journal"/>
	<res alias="BestiarySpiderEP2"									path="dlc\bob\journal\bestiary\ep2arachnomorphs.journal"/>
	<res alias="BestiaryBoarEP2"									path="dlc\bob\journal\bestiary\ep2boar.journal"/>
	

	
<!-- EP2 TUTORIALS -->
	
	<!-- ingame welcome messages -->
	<res alias="TutorialEP2Standalone" 								path="gameplay\journal\tutorial\ep2standalone.journal"/>
	<res alias="TutorialEP2FinishQ305" 								path="gameplay\journal\tutorial\ep2finishq305.journal"/>
	<res alias="TutorialEP2AfterQ305" 								path="gameplay\journal\tutorial\ep2afterq305.journal"/>
	<res alias="TutorialEP2NoStandalonesQ305Done" 					path="gameplay\journal\tutorial\ep2nostandalonesq305done.journal"/>
	<res alias="TutorialEP2NewFeatures" 							path="gameplay\journal\tutorial\ep2newfeatures.journal"/>
	<res alias="TutorialEP1AndEP2Standalone" 						path="gameplay\journal\tutorial\ep1andep2standalone.journal"/>
	<res alias="TutorialEP2SpendSkillpoints" 						path="gameplay\journal\tutorial\ep2spendskillpoints.journal"/>
	
	<!-- dye -->
	<res alias="TutorialDye" 										path="gameplay\journal\tutorial\dye.journal"/>
	<res alias="TutorialDye2" 										path="gameplay\journal\tutorial\dye2.journal"/>
	<res alias="TutorialDyeRemover" 								path="gameplay\journal\tutorial\dyeremover.journal"/>
	<res alias="TutorialJournalDye" 								path="gameplay\journal\tutorial\jedye.journal"/>
	<res alias="TutorialJournalDye_pad"								path="gameplay\journal\tutorial\jedyepad.journal"/>
	<res alias="TutorialDyePreview" 								path="gameplay\journal\tutorial\dyepreview.journal"/>
	<res alias="TutorialDyePreview_pad" 							path="gameplay\journal\tutorial\dyepreviewpad.journal"/>
	
	<!-- map -->
	<res alias="TutorialMapEP2QuestPins" 							path="gameplay\journal\tutorial\mapep2questpins.journal"/>
	
	<!-- mutagen dismantling table -->
	<res alias="TutorialMutagenTableDescription"					path="gameplay\journal\tutorial\mutagentabledescription.journal"/>
	<res alias="TutorialMutagenTableWhyDoIt"						path="gameplay\journal\tutorial\mutagentablewhydoit.journal"/>
	<res alias="TutorialJournalMutagenTable"						path="gameplay\journal\tutorial\jemutagentable.journal"/>
	
	<!-- mutations -->
	<res alias="TutorialMutationsUnlocked"							path="gameplay\journal\tutorial\mutationsunlocked.journal"/>
	<res alias="TutorialMutationsOpenMutations"						path="gameplay\journal\tutorial\mutationsopenmutations.journal"/>
	<res alias="TutorialMutationsMissingResources"					path="gameplay\journal\tutorial\mutationsmissingresources.journal"/>	
	<res alias="TutorialMutationsSelectAdvMutation"					path="gameplay\journal\tutorial\mutationselectadvmutation.journal"/>
	<res alias="TutorialMutationsPrerequisites"						path="gameplay\journal\tutorial\mutationsprerequisites.journal"/>
	<res alias="TutorialMutationsEquipping"							path="gameplay\journal\tutorial\mutationsequipping.journal"/>
	<res alias="TutorialMutationsEquippingOnlyOne"					path="gameplay\journal\tutorial\mutationsequippingonlyone.journal"/>
	<res alias="TutorialMutationsMasterMutation"					path="gameplay\journal\tutorial\mutationsmastermutation.journal"/>
	<res alias="TutorialMutationsOpenCharPanel"						path="gameplay\journal\tutorial\mutationsopencharpanel.journal"/>
	<res alias="TutorialMutationsEquippedCharPanel"					path="gameplay\journal\tutorial\mutationsequippedcharpanel.journal"/>
	<res alias="TutorialMutationsMutagens"							path="gameplay\journal\tutorial\mutationsmutagens.journal"/>
	<res alias="TutorialMutationsMasterLevelUp"						path="gameplay\journal\tutorial\mutationsmasterlevelup.journal"/>
	<res alias="TutorialMutationsAdditionalSkillSlot"				path="gameplay\journal\tutorial\mutationsadditionalskillslot.journal"/>
	<res alias="TutorialMutationsSlotColorMatching"					path="gameplay\journal\tutorial\mutationsslotcolormatching.journal"/>
	<res alias="TutorialMutationsYellowMutations"					path="gameplay\journal\tutorial\mutationsyellowmutations.journal"/>
	<res alias="TutorialMutationsSelect"							path="gameplay\journal\tutorial\mutationsselect.journal"/>
	<res alias="TutorialMutationsResearching"						path="gameplay\journal\tutorial\mutationsresearching.journal"/>
	<res alias="TutorialJournalMutationsDescription"				path="gameplay\journal\tutorial\jemutationsdescription.journal"/>
	<res alias="TutorialJournalMutationsMasterMutation"				path="gameplay\journal\tutorial\jemutationsmastermutation.journal"/>
	<res alias="TutorialJournalMutationsResearch"					path="gameplay\journal\tutorial\jemutationsresearch.journal"/>
	
	<!-- set bonuses -->
	<res alias="TutorialSetBonusesInfo" 							path="gameplay\journal\tutorial\setbonusesinfo.journal"/>
	<res alias="TutorialSetBonusesUnlocked" 						path="gameplay\journal\tutorial\setbonusesunlocked.journal"/>
	<res alias="TutorialJournalSetBonuses" 							path="gameplay\journal\tutorial\jesetbonuses.journal"/>
	
	<!-- living world -->
	<res alias="TutorialJournalLebioda" 							path="gameplay\journal\tutorial\tutorialjournallebioda.journal"/>
	<res alias="TutorialJournalHansa" 								path="gameplay\journal\tutorial\tutorialjournalhansa.journal"/>
	<res alias="LebiodaBuildingInfo" 								path="gameplay\journal\tutorial\lebiodabuildinginfo.journal"/>
	<res alias="WineWarsInfo" 										path="gameplay\journal\tutorial\wineWarsinfo.journal"/>
	<res alias="HansaAfterEffects" 									path="gameplay\journal\tutorial\hansaaftereffects.journal"/>
	<res alias="ErrantKnight" 										path="gameplay\journal\tutorial\errantknight.journal"/>
	<res alias="New_BaW_POI" 										path="gameplay\journal\tutorial\newbawpois.journal"/>
	<res alias="CamerlingReward" 									path="gameplay\journal\tutorial\camerlingreward.journal"/>

	<!-- sq701 horse combat tutorial -->
	<res alias="TutorialHorseCombat" 								path="gameplay\journal\tutorial\horsecombat.journal"/>

	<!-- Witcher House Features -->
	<res alias="TutorialEP2mq7024HouseGreenhouse"					path="gameplay\journal\tutorial\ep2housegardentutorial.journal"/>
	<res alias="TutorialEP2mq7024HouseOrchard"						path="gameplay\journal\tutorial\ep2housegardenorchardtutorial.journal"/>

	<!-- Testing -->
	<res alias="BestiaryQCBeastOfBeauclaire"						path="dlc\bob\journal\bestiary\ep2beast.journal"/>				
	<res alias="BestiaryQCPigs"										path="dlc\bob\journal\bestiary\q704threelittlepigs.journal"/>
	<res alias="BestiaryQCDracolizardMatriarch"						path="dlc\bob\journal\bestiary\mq7010dracolizard.journal"/>
	<res alias="BestiaryQCSilverBasilisk"							path="dlc\bob\journal\bestiary\mq7018basilisk.journal"/>
	<res alias="BestiaryQCSharleyMatriarch" 						path="dlc\bob\journal\bestiary\bestiarymonsterhuntmh701.journal"/>
	<res alias="BestiaryQCSpriggan" 								path="dlc\bob\journal\bestiary\mq7002spriggan.journal"/>
	<res alias="BestiaryQCSharleyCaptive" 							path="dlc\bob\journal\bestiary\q701sharley.journal"/>
	<res alias="BestiaryQCFTWitch" 									path="dlc\bob\journal\bestiary\q704ftwitch.journal"/>
	<res alias="BestiaryQCNightmare" 								path="dlc\bob\journal\bestiary\bestiarymonsterhuntmq7017.journal"/>
	<res alias="BestiaryQCDaphne" 									path="dlc\bob\journal\bestiary\bestiarymq7004.journal"/>
	<res alias="BestiaryQCRapunzel" 								path="dlc\bob\journal\bestiary\q704rapunzel.journal"/>
	<res alias="BestiaryQCBruxaCB" 									path="dlc\bob\journal\bestiary\q701bruxa.journal"/>
	<res alias="BestiaryQCAlphaGarkain" 							path="dlc\bob\journal\bestiary\q704alphagarkain.journal"/>
	<res alias="BestiaryQCDettlaff" 								path="dlc\bob\journal\bestiary\dettlaffmonster.journal"/>
	<res alias="BestiaryQCWightCollector" 							path="dlc\bob\journal\bestiary\q702wight.journal"/>
	<res alias="BestiaryQCBigBadWolf" 								path="dlc\bob\journal\bestiary\q704bigbadwolfasbeast.journal"/>
	<res alias="BestiaryQCMoreauGolem" 								path="dlc\bob\journal\bestiary\moreausgolem.journal"/>
	<res alias="BestiaryQCProtofleder" 								path="dlc\bob\journal\bestiary\protofleder.journal"/>
	<res alias="BestiaryQCEP2Boar" 									path="dlc\bob\journal\bestiary\ep2boar.journal"/>
	<res alias="BestiaryQCMQ7002Borowy"								path="dlc\bob\journal\bestiary\mq7002grotte.journal"/>
	<res alias="BestiaryQCBeanshee"									path="dlc\bob\journal\bestiary\beanshie.journal"/>
	
	<res alias="CharactersAnnaHenrietta" 							path="dlc\bob\journal\characters\annahenrietta.journal"/>
	<res alias="CharactersDamien" 									path="dlc\bob\journal\characters\damien.journal"/>
	<res alias="CharactersDettlaff" 								path="dlc\bob\journal\characters\dettlaff.journal"/>
	<res alias="CharactersGuillaume" 								path="dlc\bob\journal\characters\guillaumedepeyracpeyran.journal"/>
	<res alias="CharactersMilton" 									path="dlc\bob\journal\characters\milton.journal"/>
	<res alias="CharactersOriana" 									path="dlc\bob\journal\characters\oriana.journal"/>
	<res alias="CharactersPalmerin" 								path="dlc\bob\journal\characters\palmerin.journal"/>
	<res alias="CharactersRegis" 									path="dlc\bob\journal\characters\regis.journal"/>
	<res alias="CharactersSyanna" 									path="dlc\bob\journal\characters\syanna.journal"/>
	<res alias="CharactersUkryty" 									path="dlc\bob\journal\characters\ukryty.journal"/>
	<res alias="CharactersVivienne" 								path="dlc\bob\journal\characters\vivienne.journal"/>
	<res alias="CharactersHermit" 									path="dlc\bob\journal\characters\hermitoflaccelavy.journal"/>
	<res alias="CharactersLadyOfTheLake" 							path="dlc\bob\journal\characters\ladyofthelake.journal"/>
	<res alias="CharactersBarnabe"	 								path="dlc\bob\journal\characters\barnabe-basilefawlty.journal"/>
	<res alias="CharactersBootblack" 								path="dlc\bob\journal\characters\bootblack.journal"/>
	<res alias="CharactersRoach" 									path="dlc\bob\journal\characters\roach.journal"/>

	
	<!-- Dettlaff Bossfight Entities -->
	<res alias="dettlaff_minion"									path="dlc\bob\data\quests\main_quests\quest_files\q704_truth\characters\detlaff_construct.w2ent"/>
	<res alias="dettlaff_cocoon" 									path="dlc\bob\data\fx\monsters\dettlaff\monster\dettlaff_cocoon_with_dettlaff.w2ent"/>
	<res alias="dettlaff_vein_01" 									path="dlc\bob\data\fx\monsters\dettlaff\monster\dettlaff_veiny_001.w2ent"/>
	<res alias="dettlaff_vein_02" 									path="dlc\bob\data\fx\monsters\dettlaff\monster\dettlaff_veiny_002.w2ent"/>
	<res alias="dettlaff_vein_03" 									path="dlc\bob\data\fx\monsters\dettlaff\monster\dettlaff_veiny_003.w2ent"/>
	<res alias="dettlaff_arena" 									path="dlc\bob\data\fx\monsters\dettlaff\monster\dettlaff_arena.w2ent"/>
	<res alias="dettlaff_arena_ground" 								path="dlc\bob\data\fx\monsters\dettlaff\monster\dettlaff_arena_ground.w2ent"/>

	<!-- player inventories for preview -->
	<res alias="preview_inventory_red_wolf_1" 				path="dlc\bob\data\characters\npc_entities\player_entities\geralt\geralt_inventory_debug\geralt_inventory_debug__red_wolf_lvl1.w2ent" />
</resources>
